include/OpenXLSX/headers/IZipArchive.hpp
include/OpenXLSX/headers/OpenXLSX-Exports.hpp
include/OpenXLSX/headers/XLCell.hpp
include/OpenXLSX/headers/XLCellIterator.hpp
include/OpenXLSX/headers/XLCellRange.hpp
include/OpenXLSX/headers/XLCellReference.hpp
include/OpenXLSX/headers/XLCellValue.hpp
include/OpenXLSX/headers/XLColor.hpp
include/OpenXLSX/headers/XLColumn.hpp
include/OpenXLSX/headers/XLCommandQuery.hpp
include/OpenXLSX/headers/XLComments.hpp
include/OpenXLSX/headers/XLConstants.hpp
include/OpenXLSX/headers/XLContentTypes.hpp
include/OpenXLSX/headers/XLDateTime.hpp
include/OpenXLSX/headers/XLDocument.hpp
include/OpenXLSX/headers/XLDrawing.hpp
include/OpenXLSX/headers/XLException.hpp
include/OpenXLSX/headers/XLFormula.hpp
include/OpenXLSX/headers/XLIterator.hpp
include/OpenXLSX/headers/XLMergeCells.hpp
include/OpenXLSX/headers/XLProperties.hpp
include/OpenXLSX/headers/XLRelationships.hpp
include/OpenXLSX/headers/XLRow.hpp
include/OpenXLSX/headers/XLRowData.hpp
include/OpenXLSX/headers/XLSharedStrings.hpp
include/OpenXLSX/headers/XLSheet.hpp
include/OpenXLSX/headers/XLStyles.hpp
include/OpenXLSX/headers/XLTables.hpp
include/OpenXLSX/headers/XLWorkbook.hpp
include/OpenXLSX/headers/XLXmlData.hpp
include/OpenXLSX/headers/XLXmlFile.hpp
include/OpenXLSX/headers/XLXmlParser.hpp
include/OpenXLSX/headers/XLZipArchive.hpp
include/OpenXLSX/OpenXLSX.hpp
include/pybind11_json/pybind11_json.hpp
lib/cmake/OpenXLSX/OpenXLSXConfig.cmake
lib/cmake/OpenXLSX/OpenXLSXConfigVersion.cmake
lib/cmake/OpenXLSX/OpenXLSXTargets-release.cmake
lib/cmake/OpenXLSX/OpenXLSXTargets.cmake
lib/OpenXLSX.lib
PyThor.cp312-win_amd64.pyd
share/cmake/pybind11_json/pybind11_jsonConfig.cmake
share/cmake/pybind11_json/pybind11_jsonConfigVersion.cmake
share/cmake/pybind11_json/pybind11_jsonTargets.cmake
share/pkgconfig/pybind11_json.pc
pythor-0.1.1.dist-info/METADATA
pythor-0.1.1.dist-info/WHEEL
pythor-0.1.1.dist-info/RECORD
